AUTHORS.txt
CHANGELOG.txt
LICENSE.txt
README.txt
setup.py
coopr/__init__.py
coopr.colin.egg-info/PKG-INFO
coopr.colin.egg-info/SOURCES.txt
coopr.colin.egg-info/dependency_links.txt
coopr.colin.egg-info/entry_points.txt
coopr.colin.egg-info/namespace_packages.txt
coopr.colin.egg-info/top_level.txt
coopr/colin/__init__.py
coopr/colin/results_attributes.py
coopr/colin/core/__init__.py
coopr/colin/core/colin_xml_io.py
coopr/colin/core/dakota_text_io.py
coopr/colin/core/point.py
coopr/colin/core/problem.py
coopr/colin/core/problem_io.py
coopr/colin/core/solver.py
coopr/colin/solver/__init__.py
coopr/colin/solver/ps.py
coopr/colin/tests/__init__.py
coopr/colin/tests/core/__init__.py
coopr/colin/tests/core/test1_ps.txt
coopr/colin/tests/core/test2_ps.txt
coopr/colin/tests/core/test_parallel.py
coopr/colin/tests/core/test_problem.py
coopr/colin/tests/core/test_ps.py
doc/opt/Makefile
doc/opt/coopr.bib
doc/opt/macros.tex
doc/opt/plugins-coopr.tex
doc/opt/plugins-intro.tex
doc/opt/plugins-pca.tex
doc/opt/plugins.tex
examples/colin/README.txt
examples/colin/colin/dakota.in
examples/colin/colin/dakota_fn1
examples/colin/colin/example_fn1
examples/colin/colin/example_fn2
examples/colin/colin/example_fn3
examples/colin/colin/example_fn4
examples/colin/colin/request.xml